calculator.py
scipy_calculator-1.0.0.dist-info/LICENSE.txt
scipy_calculator-1.0.0.dist-info/METADATA
scipy_calculator-1.0.0.dist-info/WHEEL
scipy_calculator-1.0.0.dist-info/top_level.txt
scipy_calculator-1.0.0.dist-info/RECORD
