Metadata-Version: 2.1
Name: scipy-calculator
Version: 1.0.0
Summary: A Scientific calculator
Home-page: https://github.com/komus/scipy_calculator
Author: Oyindolapo Komolafe
Author-email: oyindolapokomolafe@yahoo.com
License: UNKNOWN
Platform: UNKNOWN
Classifier: Programming Language :: Python :: 3
Classifier: Programming Language :: Python :: 3.8
Classifier: Programming Language :: Python :: 3.9
Classifier: License :: OSI Approved :: MIT License
Classifier: Operating System :: OS Independent
Requires-Dist: multipledispatch (~=0.6.0)
Provides-Extra: dev
Requires-Dist: pytest (>=3.7) ; extra == 'dev'
